Workbook

Sheet Dashboard
B2: Lead Tracker & Call Kit
B3: Prepared by Andrei Rubic | SAMPLE WITH DUMMY DATA
B4: Report date | C4: 46308
B6: Key numbers
B7: Total leads | C7: =COUNTA('Lead Tracker'!$A$3:$A$32) -> 30
B8: Contacted (any status after New) | C8: =COUNTA('Lead Tracker'!$A$3:$A$32)-COUNTIF('Lead Tracker'!$L$3:$L$32,"New") -> 27
B9: Viewings set | C9: =COUNTIF('Lead Tracker'!$L$3:$L$32,"Viewing set") -> 5
B10: Closed | C10: =COUNTIF('Lead Tracker'!$L$3:$L$32,"Closed") -> 1
B11: Follow-ups overdue | C11: =COUNTIF('Lead Tracker'!$P$3:$P$32,"Overdue") -> 4
B12: Follow-ups due today or soon | C12: =COUNTIF('Lead Tracker'!$P$3:$P$32,"Due today")+COUNTIF('Lead Tracker'!$P$3:$P$32,"Due soon") -> 7
B13: Close rate (closed / total) | C13: =IFERROR(COUNTIF('Lead Tracker'!$L$3:$L$32,"Closed")/COUNTA('Lead Tracker'!$A$3:$A$32),0) -> 0.033333333
B15: Leads by status | E15: Leads by source
B16: Status | C16: Leads | E16: Source | F16: Leads
B17: New | C17: =COUNTIF('Lead Tracker'!$L$3:$L$32,B17) -> 3 | E17: Online listing | F17: =COUNTIF('Lead Tracker'!$F$3:$F$32,E17) -> 10
B18: Contacted | C18: =COUNTIF('Lead Tracker'!$L$3:$L$32,B18) -> 15 | E18: Referral | F18: =COUNTIF('Lead Tracker'!$F$3:$F$32,E18) -> 9
B19: Viewing set | C19: =COUNTIF('Lead Tracker'!$L$3:$L$32,B19) -> 5 | E19: Walk-in | F19: =COUNTIF('Lead Tracker'!$F$3:$F$32,E19) -> 6
B20: Negotiating | C20: =COUNTIF('Lead Tracker'!$L$3:$L$32,B20) -> 4 | E20: Cold call | F20: =COUNTIF('Lead Tracker'!$F$3:$F$32,E20) -> 5
B21: Closed | C21: =COUNTIF('Lead Tracker'!$L$3:$L$32,B21) -> 1
B22: Dropped | C22: =COUNTIF('Lead Tracker'!$L$3:$L$32,B22) -> 2 | E22: Leads by type
E23: Seller | F23: =COUNTIF('Lead Tracker'!$D$3:$D$32,E23) -> 14
E24: Buyer | F24: =COUNTIF('Lead Tracker'!$D$3:$D$32,E24) -> 16

Sheet Lead Tracker
A1: SAMPLE DATA: all names, numbers, and notes are fictional and for illustration only
A2: Lead ID | B2: Date Added | C2: Lead | D2: Type | E2: Contact (dummy) | F2: Source | G2: Interest / Location | H2: Budget or Asking (PHP) | I2: Last Call | J2: Call Outcome | K2: Priority | L2: Status | M2: Next Action | N2: Follow-up Date | O2: Days to Follow-up | P2: Follow-up Flag | Q2: Notes
A3: LD-001 | B3: 46271 | C3: Seller 01 (sample) | D3: Seller | E3: 0900 000 0001 | F3: Online listing | G3: House & lot, Cainta | H3: 3200000 | K3: Low | L3: New | M3: Make first call | N3: 46320 | O3: =IF(OR(N3="",L3="Closed",L3="Dropped"),"",N3-Dashboard!$C$4) -> 12 | P3: =IF(O3="","",IF(O3<0,"Overdue",IF(O3=0,"Due today",IF(O3<=2,"Due soon","On track")))) -> On track | Q3: EXAMPLE ROW: shows the expected format. Replace with your own leads.
A4: LD-002 | B4: 46271 | C4: Buyer 02 (sample) | D4: Buyer | E4: 0900 000 0002 | F4: Online listing | G4: Townhouse in General Trias | H4: 5000000 | I4: 46272 | J4: Call back requested | K4: Low | L4: Viewing set | M4: Confirm viewing | N4: 46314 | O4: =IF(OR(N4="",L4="Closed",L4="Dropped"),"",N4-Dashboard!$C$4) -> 6 | P4: =IF(O4="","",IF(O4<0,"Overdue",IF(O4=0,"Due today",IF(O4<=2,"Due soon","On track")))) -> On track
A5: LD-003 | B5: 46272 | C5: Buyer 03 (sample) | D5: Buyer | E5: 0900 000 0003 | F5: Referral | G5: Townhouse in Silang | H5: 5000000 | I5: 46273 | J5: Answered - interested | K5: High | L5: Negotiating | M5: Send offer update | N5: 46304 | O5: =IF(OR(N5="",L5="Closed",L5="Dropped"),"",N5-Dashboard!$C$4) -> -4 | P5: =IF(O5="","",IF(O5<0,"Overdue",IF(O5=0,"Due today",IF(O5<=2,"Due soon","On track")))) -> Overdue
A6: LD-004 | B6: 46272 | C6: Seller 04 (sample) | D6: Seller | E6: 0900 000 0004 | F6: Cold call | G6: House & lot, Antipolo | H6: 3200000 | I6: 46273 | J6: Answered - not now | K6: Medium | L6: Contacted | M6: Send recap email | N6: 46316 | O6: =IF(OR(N6="",L6="Closed",L6="Dropped"),"",N6-Dashboard!$C$4) -> 8 | P6: =IF(O6="","",IF(O6<0,"Overdue",IF(O6=0,"Due today",IF(O6<=2,"Due soon","On track")))) -> On track
A7: LD-005 | B7: 46272 | C7: Seller 05 (sample) | D7: Seller | E7: 0900 000 0005 | F7: Cold call | G7: House & lot, Bacoor | H7: 2500000 | I7: 46273 | J7: Answered - not now | K7: Medium | L7: Negotiating | M7: Send offer update | N7: 46320 | O7: =IF(OR(N7="",L7="Closed",L7="Dropped"),"",N7-Dashboard!$C$4) -> 12 | P7: =IF(O7="","",IF(O7<0,"Overdue",IF(O7=0,"Due today",IF(O7<=2,"Due soon","On track")))) -> On track | Q7: Prefers calls after 5 PM (sample note)
A8: LD-006 | B8: 46274 | C8: Buyer 06 (sample) | D8: Buyer | E8: 0900 000 0006 | F8: Walk-in | G8: House & lot in Cainta | H8: 1500000 | I8: 46277 | J8: Answered - interested | K8: Medium | L8: Contacted | M8: Send recap email | N8: 46316 | O8: =IF(OR(N8="",L8="Closed",L8="Dropped"),"",N8-Dashboard!$C$4) -> 8 | P8: =IF(O8="","",IF(O8<0,"Overdue",IF(O8=0,"Due today",IF(O8<=2,"Due soon","On track")))) -> On track
A9: LD-007 | B9: 46277 | C9: Seller 07 (sample) | D9: Seller | E9: 0900 000 0007 | F9: Referral | G9: House & lot, Antipolo | H9: 4500000 | I9: 46280 | J9: Answered - not now | K9: Low | L9: Contacted | M9: Send recap email | N9: 46309 | O9: =IF(OR(N9="",L9="Closed",L9="Dropped"),"",N9-Dashboard!$C$4) -> 1 | P9: =IF(O9="","",IF(O9<0,"Overdue",IF(O9=0,"Due today",IF(O9<=2,"Due soon","On track")))) -> Due soon
A10: LD-008 | B10: 46278 | C10: Buyer 08 (sample) | D10: Buyer | E10: 0900 000 0008 | F10: Referral | G10: House & lot in Dasmariñas | H10: 4000000 | I10: 46279 | J10: Answered - not now | K10: Medium | L10: Negotiating | M10: Send offer update | N10: 46309 | O10: =IF(OR(N10="",L10="Closed",L10="Dropped"),"",N10-Dashboard!$C$4) -> 1 | P10: =IF(O10="","",IF(O10<0,"Overdue",IF(O10=0,"Due today",IF(O10<=2,"Due soon","On track")))) -> Due soon
A11: LD-009 | B11: 46279 | C11: Seller 09 (sample) | D11: Seller | E11: 0900 000 0009 | F11: Referral | G11: Residential lot, Dasmariñas | H11: 4500000 | I11: 46280 | J11: Call back requested | K11: Low | L11: Contacted | M11: Send recap email | N11: 46315 | O11: =IF(OR(N11="",L11="Closed",L11="Dropped"),"",N11-Dashboard!$C$4) -> 7 | P11: =IF(O11="","",IF(O11<0,"Overdue",IF(O11=0,"Due today",IF(O11<=2,"Due soon","On track")))) -> On track
A12: LD-010 | B12: 46279 | C12: Buyer 10 (sample) | D12: Buyer | E12: 0900 000 0010 | F12: Online listing | G12: Lot in Dasmariñas | H12: 1500000 | K12: High | L12: New | M12: Make first call | N12: 46313 | O12: =IF(OR(N12="",L12="Closed",L12="Dropped"),"",N12-Dashboard!$C$4) -> 5 | P12: =IF(O12="","",IF(O12<0,"Overdue",IF(O12=0,"Due today",IF(O12<=2,"Due soon","On track")))) -> On track | Q12: Asked for photos of the lot (sample note)
A13: LD-011 | B13: 46279 | C13: Seller 11 (sample) | D13: Seller | E13: 0900 000 0011 | F13: Online listing | G13: House & lot, Bacoor | H13: 1800000 | I13: 46280 | J13: Answered - interested | K13: Low | L13: Negotiating | M13: Send offer update | N13: 46313 | O13: =IF(OR(N13="",L13="Closed",L13="Dropped"),"",N13-Dashboard!$C$4) -> 5 | P13: =IF(O13="","",IF(O13<0,"Overdue",IF(O13=0,"Due today",IF(O13<=2,"Due soon","On track")))) -> On track
A14: LD-012 | B14: 46281 | C14: Seller 12 (sample) | D14: Seller | E14: 0900 000 0012 | F14: Online listing | G14: Commercial lot, Cainta | H14: 1800000 | I14: 46282 | J14: No answer | K14: Low | L14: Contacted | M14: Send recap email | N14: 46304 | O14: =IF(OR(N14="",L14="Closed",L14="Dropped"),"",N14-Dashboard!$C$4) -> -4 | P14: =IF(O14="","",IF(O14<0,"Overdue",IF(O14=0,"Due today",IF(O14<=2,"Due soon","On track")))) -> Overdue
A15: LD-013 | B15: 46281 | C15: Buyer 13 (sample) | D15: Buyer | E15: 0900 000 0013 | F15: Referral | G15: Lot in Imus | H15: 5000000 | I15: 46282 | J15: No answer | K15: High | L15: Contacted | M15: Send recap email | N15: 46306 | O15: =IF(OR(N15="",L15="Closed",L15="Dropped"),"",N15-Dashboard!$C$4) -> -2 | P15: =IF(O15="","",IF(O15<0,"Overdue",IF(O15=0,"Due today",IF(O15<=2,"Due soon","On track")))) -> Overdue
A16: LD-014 | B16: 46285 | C16: Buyer 14 (sample) | D16: Buyer | E16: 0900 000 0014 | F16: Walk-in | G16: Lot in Imus | H16: 4000000 | I16: 46288 | J16: Call back requested | K16: Medium | L16: Contacted | M16: Send recap email | N16: 46315 | O16: =IF(OR(N16="",L16="Closed",L16="Dropped"),"",N16-Dashboard!$C$4) -> 7 | P16: =IF(O16="","",IF(O16<0,"Overdue",IF(O16=0,"Due today",IF(O16<=2,"Due soon","On track")))) -> On track
A17: LD-015 | B17: 46288 | C17: Seller 15 (sample) | D17: Seller | E17: 0900 000 0015 | F17: Walk-in | G17: House & lot, Antipolo | H17: 6000000 | K17: Medium | L17: New | M17: Make first call | N17: 46315 | O17: =IF(OR(N17="",L17="Closed",L17="Dropped"),"",N17-Dashboard!$C$4) -> 7 | P17: =IF(O17="","",IF(O17<0,"Overdue",IF(O17=0,"Due today",IF(O17<=2,"Due soon","On track")))) -> On track
A18: LD-016 | B18: 46289 | C18: Seller 16 (sample) | D18: Seller | E18: 0900 000 0016 | F18: Walk-in | G18: House & lot, Cainta | H18: 7500000 | I18: 46291 | J18: Answered - interested | K18: High | L18: Contacted | M18: Send recap email | N18: 46320 | O18: =IF(OR(N18="",L18="Closed",L18="Dropped"),"",N18-Dashboard!$C$4) -> 12 | P18: =IF(O18="","",IF(O18<0,"Overdue",IF(O18=0,"Due today",IF(O18<=2,"Due soon","On track")))) -> On track
A19: LD-017 | B19: 46290 | C19: Buyer 17 (sample) | D19: Buyer | E19: 0900 000 0017 | F19: Referral | G19: Townhouse in Taytay | H19: 2200000 | I19: 46293 | J19: Answered - not now | K19: High | L19: Contacted | M19: Send recap email | N19: 46309 | O19: =IF(OR(N19="",L19="Closed",L19="Dropped"),"",N19-Dashboard!$C$4) -> 1 | P19: =IF(O19="","",IF(O19<0,"Overdue",IF(O19=0,"Due today",IF(O19<=2,"Due soon","On track")))) -> Due soon
A20: LD-018 | B20: 46290 | C20: Seller 18 (sample) | D20: Seller | E20: 0900 000 0018 | F20: Online listing | G20: House & lot, Taytay | H20: 4500000 | I20: 46291 | J20: No answer | K20: High | L20: Contacted | M20: Send recap email | N20: 46320 | O20: =IF(OR(N20="",L20="Closed",L20="Dropped"),"",N20-Dashboard!$C$4) -> 12 | P20: =IF(O20="","",IF(O20<0,"Overdue",IF(O20=0,"Due today",IF(O20<=2,"Due soon","On track")))) -> On track | Q20: Spouse joins the viewing (sample note)
A21: LD-019 | B21: 46294 | C21: Buyer 19 (sample) | D21: Buyer | E21: 0900 000 0019 | F21: Cold call | G21: House & lot in Silang | H21: 5000000 | I21: 46297 | J21: Answered - interested | L21: Closed | O21: =IF(OR(N21="",L21="Closed",L21="Dropped"),"",N21-Dashboard!$C$4) | P21: =IF(O21="","",IF(O21<0,"Overdue",IF(O21=0,"Due today",IF(O21<=2,"Due soon","On track"))))
A22: LD-020 | B22: 46297 | C22: Seller 20 (sample) | D22: Seller | E22: 0900 000 0020 | F22: Referral | G22: Commercial lot, Antipolo | H22: 3200000 | I22: 46300 | J22: Call back requested | K22: Low | L22: Contacted | M22: Send recap email | N22: 46313 | O22: =IF(OR(N22="",L22="Closed",L22="Dropped"),"",N22-Dashboard!$C$4) -> 5 | P22: =IF(O22="","",IF(O22<0,"Overdue",IF(O22=0,"Due today",IF(O22<=2,"Due soon","On track")))) -> On track
A23: LD-021 | B23: 46298 | C23: Buyer 21 (sample) | D23: Buyer | E23: 0900 000 0021 | F23: Online listing | G23: Lot in Bacoor | H23: 3000000 | I23: 46299 | J23: Call back requested | K23: Low | L23: Contacted | M23: Send recap email | N23: 46309 | O23: =IF(OR(N23="",L23="Closed",L23="Dropped"),"",N23-Dashboard!$C$4) -> 1 | P23: =IF(O23="","",IF(O23<0,"Overdue",IF(O23=0,"Due today",IF(O23<=2,"Due soon","On track")))) -> Due soon
A24: LD-022 | B24: 46299 | C24: Buyer 22 (sample) | D24: Buyer | E24: 0900 000 0022 | F24: Referral | G24: Townhouse in Silang | H24: 1500000 | I24: 46300 | J24: Answered - interested | K24: Medium | L24: Contacted | M24: Send recap email | N24: 46314 | O24: =IF(OR(N24="",L24="Closed",L24="Dropped"),"",N24-Dashboard!$C$4) -> 6 | P24: =IF(O24="","",IF(O24<0,"Overdue",IF(O24=0,"Due today",IF(O24<=2,"Due soon","On track")))) -> On track
A25: LD-023 | B25: 46300 | C25: Seller 23 (sample) | D25: Seller | E25: 0900 000 0023 | F25: Walk-in | G25: House & lot, Taytay | H25: 3200000 | I25: 46302 | J25: Answered - not now | K25: Medium | L25: Viewing set | M25: Confirm viewing | N25: 46308 | O25: =IF(OR(N25="",L25="Closed",L25="Dropped"),"",N25-Dashboard!$C$4) -> 0 | P25: =IF(O25="","",IF(O25<0,"Overdue",IF(O25=0,"Due today",IF(O25<=2,"Due soon","On track")))) -> Due today
A26: LD-024 | B26: 46300 | C26: Buyer 24 (sample) | D26: Buyer | E26: 0900 000 0024 | F26: Cold call | G26: Townhouse in General Trias | H26: 1500000 | I26: 46303 | J26: Answered - interested | K26: Medium | L26: Viewing set | M26: Confirm viewing | N26: 46306 | O26: =IF(OR(N26="",L26="Closed",L26="Dropped"),"",N26-Dashboard!$C$4) -> -2 | P26: =IF(O26="","",IF(O26<0,"Overdue",IF(O26=0,"Due today",IF(O26<=2,"Due soon","On track")))) -> Overdue
A27: LD-025 | B27: 46301 | C27: Buyer 25 (sample) | D27: Buyer | E27: 0900 000 0025 | F27: Online listing | G27: House & lot in Imus | H27: 5000000 | I27: 46302 | J27: Answered - not now | K27: Medium | L27: Viewing set | M27: Confirm viewing | N27: 46309 | O27: =IF(OR(N27="",L27="Closed",L27="Dropped"),"",N27-Dashboard!$C$4) -> 1 | P27: =IF(O27="","",IF(O27<0,"Overdue",IF(O27=0,"Due today",IF(O27<=2,"Due soon","On track")))) -> Due soon
A28: LD-026 | B28: 46301 | C28: Buyer 26 (sample) | D28: Buyer | E28: 0900 000 0026 | F28: Online listing | G28: Townhouse in Cainta | H28: 3000000 | I28: 46303 | J28: Answered - interested | K28: Medium | L28: Contacted | M28: Send recap email | N28: 46314 | O28: =IF(OR(N28="",L28="Closed",L28="Dropped"),"",N28-Dashboard!$C$4) -> 6 | P28: =IF(O28="","",IF(O28<0,"Overdue",IF(O28=0,"Due today",IF(O28<=2,"Due soon","On track")))) -> On track
A29: LD-027 | B29: 46301 | C29: Buyer 27 (sample) | D29: Buyer | E29: 0900 000 0027 | F29: Cold call | G29: Lot in Dasmariñas | H29: 2200000 | I29: 46303 | J29: Answered - interested | K29: High | L29: Viewing set | M29: Confirm viewing | N29: 46308 | O29: =IF(OR(N29="",L29="Closed",L29="Dropped"),"",N29-Dashboard!$C$4) -> 0 | P29: =IF(O29="","",IF(O29<0,"Overdue",IF(O29=0,"Due today",IF(O29<=2,"Due soon","On track")))) -> Due today
A30: LD-028 | B30: 46303 | C30: Seller 28 (sample) | D30: Seller | E30: 0900 000 0028 | F30: Referral | G30: Residential lot, Dasmariñas | H30: 4500000 | I30: 46304 | J30: Answered - not now | L30: Dropped | O30: =IF(OR(N30="",L30="Closed",L30="Dropped"),"",N30-Dashboard!$C$4) | P30: =IF(O30="","",IF(O30<0,"Overdue",IF(O30=0,"Due today",IF(O30<=2,"Due soon","On track"))))
A31: LD-029 | B31: 46303 | C31: Seller 29 (sample) | D31: Seller | E31: 0900 000 0029 | F31: Online listing | G31: Residential lot, Antipolo | H31: 4500000 | I31: 46304 | J31: Call back requested | L31: Dropped | O31: =IF(OR(N31="",L31="Closed",L31="Dropped"),"",N31-Dashboard!$C$4) | P31: =IF(O31="","",IF(O31<0,"Overdue",IF(O31=0,"Due today",IF(O31<=2,"Due soon","On track"))))
A32: LD-030 | B32: 46305 | C32: Buyer 30 (sample) | D32: Buyer | E32: 0900 000 0030 | F32: Walk-in | G32: Lot in General Trias | H32: 4000000 | I32: 46307 | J32: Answered - not now | K32: Low | L32: Contacted | M32: Send recap email | N32: 46320 | O32: =IF(OR(N32="",L32="Closed",L32="Dropped"),"",N32-Dashboard!$C$4) -> 12 | P32: =IF(O32="","",IF(O32<0,"Overdue",IF(O32=0,"Due today",IF(O32<=2,"Due soon","On track")))) -> On track

Sheet Call Script
B2: Call Script (Sample)
B3: Edit the [brackets]. Keep calls short, friendly, and always end with a next step.
B5: 1. OPENING
C6: Good [morning/afternoon], may I speak with [Name]? This is Andrei, calling on behalf of [Company].
C7: I understand you're [selling/looking for] a property in [City]. Is now a good time for a quick 2-minute chat?
B9: 2A. QUESTIONS FOR SELLERS
C10: Where is the property, and what is the lot area?
C11: Is the title clean and in your name? Are the documents ready?
C12: What is your asking price, and is there room to negotiate?
C13: What is your timeline for selling, and is the property occupied?
B15: 2B. QUESTIONS FOR BUYERS
C16: What is your budget range, and how will you pay (cash, bank loan, or in-house financing)?
C17: Which cities or areas do you prefer, and what property type and size?
C18: What are your must-haves, and when do you want to move?
B20: 3. HANDLING OBJECTIONS
B21: "I'm just looking." | C21: That's fine. May I send a short list of options that match what you described? You can look at it whenever you like.
B22: "Not interested right now." | C22: Understood. Would it be okay if I check in again in [two weeks]? I'll only call if something matches your needs.
B23: "How did you get my number?" | C23: You inquired about [property / listing] on [source]. If you'd rather not be contacted, I'll note that right away.
B24: "The price is too high / too low." | C24: Thank you for telling me. Let me share recent comparable listings in [City] so we can look at the numbers together.
B25: "Call me later." | C25: Of course. What day and time works best? I'll call then and note it in my schedule.
B27: 4. CLOSING
C28: Let me confirm: [recap]. The next step is [viewing / documents / call back] on [date and time].
C29: Thank you for your time, [Name]. I'll send a short summary by email today.
B31: 5. AFTER THE CALL
C32: Log the outcome and follow-up date in the Lead Tracker the same day.
C33: Send the recap email within 24 hours (see Email Templates sheet).

Sheet Email Templates
B2: Follow-up Email Templates (Sample)
B3: Replace the [brackets] before sending. Keep each email under 120 words.
B5: Template | C5: When to use | D5: Subject | E5: Body
B6: 1. After a good call | C6: Same day, lead was interested | D6: Summary of our call: [Property / Area] | E6: Hi [Name], Thank you for speaking with me today. As discussed, you are [selling / looking for] a [property type] in [City], with [price or budget]. Next step: [viewing / documents / call back] on [date and time]. If anything above needs correcting, just reply to this email. Best regards, Andrei Rubic
B7: 2. No answer | C7: After two missed calls | D7: Trying to reach you about [Property / Area] | E7: Hi [Name], I tried calling you about [property / inquiry] but couldn't reach you. When is a good time for a short call? You can also reply here with the best time and number, and I'll follow your schedule. Best regards, Andrei Rubic
B8: 3. Viewing confirmation | C8: Day before a scheduled viewing | D8: Reminder: viewing on [date] at [time] | E8: Hi [Name], This is a friendly reminder of your viewing: Property: [address or area] Date and time: [date, time] Meeting point: [location] Please reply to confirm, or let me know if you need to reschedule. Best regards, Andrei Rubic

Sheet Read Me
B2: Lead Tracker & Call Kit: Sample Workbook
B3: SAMPLE with dummy data. Prepared by Andrei Rubic to show how I track real estate leads and follow-ups.
B5: Purpose | C5: Shows how seller and buyer leads are logged, followed up on time, and summarized for quick review.
B6: IMPORTANT | C6: All leads, names, phone numbers, prices, and notes are fictional. Nothing here is real client data or from any past employer.
B7: Sheets | C7: Dashboard (auto-calculated) | Lead Tracker (the log) | Call Script | Email Templates | Read Me.
B8: What to edit | C8: Blue-text cells on Lead Tracker, and the yellow report date on Dashboard. Everything else updates automatically.
B9: Auto-calculated | C9: Lead Tracker columns O and P (days to follow-up and flag) and all Dashboard numbers.
B10: Follow-up flag | C10: Overdue = date has passed | Due today | Due soon = within 2 days | On track. Closed and Dropped leads show no flag.
B11: Example row | C11: The row marked EXAMPLE ROW in the Notes column shows the expected format. Replace or delete it when using real data.
B12: To add leads | C12: Insert rows inside the table (above the last row) so the Dashboard formulas include them.
B13: Phone numbers | C13: Dummy numbers use the format 0900 000 0001 and are not real.
B15: Legend
B16: Blue text | C16: Input you type or paste
B17: Black text | C17: Formula (calculated automatically)
B18: Yellow cell | C18: Report date: change it to the day you are reviewing (or replace with =TODAY())
